find_keywords/__init__.py
find_keywords/find_keywords.py
find_words/__init__.py
find_words/find_keywords.py
find_words-0.0.6.dist-info/METADATA
find_words-0.0.6.dist-info/RECORD
find_words-0.0.6.dist-info/WHEEL
find_words-0.0.6.dist-info/metadata.json
find_words-0.0.6.dist-info/top_level.txt
